proyec_tito/.ipynb_checkpoints/__init__-checkpoint.py
proyec_tito/__init__.py
proyec_tito-0.1.0.dist-info/METADATA
proyec_tito-0.1.0.dist-info/WHEEL
proyec_tito-0.1.0.dist-info/RECORD
