Metadata-Version: 2.1
Name: proyec-tito
Version: 0.1.0
Summary: Este es un nuevo proyecto para America Abierta Wuw
License: MIT
Author: Mariano
Requires-Python: >=3.10,<4.0
Classifier: License :: OSI Approved :: MIT License
Classifier: Programming Language :: Python :: 3
Classifier: Programming Language :: Python :: 3.10
Classifier: Programming Language :: Python :: 3.11
Classifier: Programming Language :: Python :: 3.12
Classifier: Programming Language :: Python :: 3.13
